authz/__init__.py
authz/auth.py
authz/base.py
authz/oauth2.py
authz-0.1.4.dist-info/LICENSE
authz-0.1.4.dist-info/METADATA
authz-0.1.4.dist-info/WHEEL
authz-0.1.4.dist-info/RECORD
