Metadata-Version: 2.1
Name: authz
Version: 0.1.4
Summary: Python SDK for the AuthZ permission system
Home-page: https://e.coding.net/cloudbase-100009281119/authz/authz-python.git
License: Apache 2.0
Author: Ann
Author-email: zhaoanke@163.com
Requires-Python: >=3.9,<4.0
Classifier: License :: Other/Proprietary License
Classifier: Programming Language :: Python :: 3
Classifier: Programming Language :: Python :: 3.9
Classifier: Programming Language :: Python :: 3.10
Classifier: Programming Language :: Python :: 3.11
Classifier: Programming Language :: Python :: 3.12
Requires-Dist: httpx[socks] (>=0.27.0,<0.28.0)
Requires-Dist: pydantic (>=2.8.0,<3.0.0)
Project-URL: Documentation, https://cloudbase-100009281119.coding.net/p/authz/d/authz-python/git/tree/main/README.md
Project-URL: Repository, https://e.coding.net/cloudbase-100009281119/authz/authz-python.git
